.travis.yml
CHANGES.rst
CONTRIBUTORS.txt
MANIFEST.in
README.rst
development.ini
setup.cfg
setup.py
kotti_link/__init__.py
kotti_link/fanstatic.py
kotti_link/resources.py
kotti_link/views.py
kotti_link.egg-info/PKG-INFO
kotti_link.egg-info/SOURCES.txt
kotti_link.egg-info/dependency_links.txt
kotti_link.egg-info/entry_points.txt
kotti_link.egg-info/not-zip-safe
kotti_link.egg-info/requires.txt
kotti_link.egg-info/top_level.txt
kotti_link/locale/README
kotti_link/locale/kotti_link.pot
kotti_link/locale/de/LC_MESSAGES/kotti_link.po
kotti_link/locale/en/LC_MESSAGES/kotti_link.po
kotti_link/static/css/style.css
kotti_link/static/css/style.min.css
kotti_link/static/img/README
kotti_link/static/js/script.js
kotti_link/static/js/script.min.js
kotti_link/templates/popup.pt
kotti_link/templates/redirect.pt
kotti_link/tests/conftest.py
kotti_link/tests/test_configure.py
kotti_link/tests/test_functional.py
kotti_link/tests/test_resources.py
kotti_link/tests/test_views.py